xtop/__init__.py
xtop/__main__.py
xtop/backend/__init__.py
xtop/backend/cpu/__init__.py
xtop/backend/cpu/apple.py
xtop/backend/gpu/__init__.py
xtop/backend/gpu/jetson.py
xtop/backend/gpu/nvidia.py
xtop/backend/npu/__init__.py
xtop/backend/npu/intel.py
xtop/frontend/__init__.py
xtop/frontend/gpu.py
xtop/frontend/npu.py
xtop/frontend/tui.py
xtop/xtopException/__init__.py
xtop/xtopException/xtopException.py
xtop/xtopUtil/__init__.py
xtop/xtopUtil/xtopUtil.py
xtop-0.5.1.dist-info/licenses/LICENSE
xtop-0.5.1.dist-info/METADATA
xtop-0.5.1.dist-info/WHEEL
xtop-0.5.1.dist-info/entry_points.txt
xtop-0.5.1.dist-info/top_level.txt
xtop-0.5.1.dist-info/RECORD
